PyExp/__init__.py
PyExp/_temp.py
PyExp/abstract_experiment.py
PyExp/abstract_manager.py
PyExp/abstract_model.py
PyExp/abstract_reader.py
PyExp/app.py
PyExp-1.1.1.dist-info/LICENSE
PyExp-1.1.1.dist-info/METADATA
PyExp-1.1.1.dist-info/WHEEL
PyExp-1.1.1.dist-info/top_level.txt
PyExp-1.1.1.dist-info/RECORD
